ed_core/__init__.py
ed_core/cache.py
ed_core/config.py
ed_core/core.py
ed_core/dyn_data.py
el_decko_core-2023.5.11.dist-info/LICENSE
el_decko_core-2023.5.11.dist-info/METADATA
el_decko_core-2023.5.11.dist-info/WHEEL
el_decko_core-2023.5.11.dist-info/entry_points.txt
el_decko_core-2023.5.11.dist-info/top_level.txt
el_decko_core-2023.5.11.dist-info/RECORD
