Metadata-Version: 2.1
Name: el-decko-core
Version: 2023.5.11
Summary: El Decko Core
License: GPL-3
Project-URL: Homepage, https://github.com/Z-Ray-Entertainment/el_decko_core
Project-URL: Bug Tracker, https://github.com/Z-Ray-Entertainment/el_decko_core/issues
Platform: Linux
License-File: LICENSE
Requires-Dist: streamdeck
Requires-Dist: Pillow
Requires-Dist: xdg ; platform_system == "Linux"
Provides-Extra: backends
Requires-Dist: el-decko-backend-obs-ws ; extra == 'backends'
Requires-Dist: el-decko-backend-mpris ; extra == 'backends'
